identifyPropositions/__init__.py
identifyPropositions/__main__.py
identifyPropositions/config.py
identifyPropositions/identify.py
identifyPropositions/util.py
syllogio_identifyPropositions-1.1.0.dist-info/LICENSE
syllogio_identifyPropositions-1.1.0.dist-info/METADATA
syllogio_identifyPropositions-1.1.0.dist-info/WHEEL
syllogio_identifyPropositions-1.1.0.dist-info/entry_points.txt
syllogio_identifyPropositions-1.1.0.dist-info/top_level.txt
syllogio_identifyPropositions-1.1.0.dist-info/RECORD
