Metadata-Version: 2.1
Name: syllogio-identifyPropositions
Version: 1.1.0
Summary: Identify natural language propositions in a written argument.
Home-page: https://github.com/syllogio/syllogio-identifyPropositions
Author: Peter Sieg
Author-email: chasingmaxwell@gmail.com
License: MIT
Platform: UNKNOWN
Requires-Dist: docopt (==0.6.2)
Requires-Dist: spacy (==2.2.1)
